liveplotlib/__init__.py
liveplotlib/get_file_format.py
liveplotlib/if_ipynb.py
liveplotlib/live_plot_only_train.py
liveplotlib/live_plot_train_and_val.py
liveplotlib-0.3.3.dist-info/LICENSE
liveplotlib-0.3.3.dist-info/METADATA
liveplotlib-0.3.3.dist-info/WHEEL
liveplotlib-0.3.3.dist-info/top_level.txt
liveplotlib-0.3.3.dist-info/RECORD
