Metadata-Version: 2.1
Name: liveplotlib
Version: 0.3.3
Summary: Library for plotting (visualizing) cost function changes during model training (in real time)
Home-page: https://github.com/pozharskyE/liveplotlib
Author: pozharskyE
Author-email: evgeny.pozharsky@gmail.com
Project-URL: Docs, https://github.com/pozharskyE/liveplotlib
Classifier: Programming Language :: Python :: 3
Classifier: License :: OSI Approved :: MIT License
Classifier: Operating System :: OS Independent
Requires-Python: >=3.7
License-File: LICENSE
Requires-Dist: PyQt5
Requires-Dist: matplotlib
